algovis/__init__.py
algovis/searching/__init__.py
algovis/searching/_animate_search.py
algovis/searching/_base_class_search.py
algovis/searching/_markdown_files/binarysearch.md
algovis/searching/_markdown_files/linearsearch.md
algovis/searching/_timer.py
algovis/searching/binarysearch.py
algovis/searching/linearsearch.py
algovis/sorting/__init__.py
algovis/sorting/_animation.py
algovis/sorting/_base_sorting.py
algovis/sorting/_markdown_files/bubblesort.md
algovis/sorting/_markdown_files/insertionsort.md
algovis/sorting/_markdown_files/mergesort.md
algovis/sorting/_markdown_files/quicksort.md
algovis/sorting/_markdown_files/selectionsort.md
algovis/sorting/_timer.py
algovis/sorting/bubblesort.py
algovis/sorting/insertionsort.py
algovis/sorting/mergesort.py
algovis/sorting/quicksort.py
algovis/sorting/selectionsort.py
algovis-0.1.6.dist-info/LICENSE
algovis-0.1.6.dist-info/WHEEL
algovis-0.1.6.dist-info/METADATA
algovis-0.1.6.dist-info/RECORD
