Metadata-Version: 2.1
Name: algovis
Version: 0.1.6
Summary: A Python library for visualising algorithms
Home-page: https://github.com/hotshot07/algovis
License: AGPL-3.0
Keywords: Visualization,Analyzing,Algorithms,Sorting,Searching
Author: hotshot07
Author-email: aroram@tcd.ie
Maintainer: hotshot07
Maintainer-email: aroram@tcd.ie
Requires-Python: >=3.7.0,<4.0.0
Classifier: License :: OSI Approved :: GNU Affero General Public License v3
Classifier: Programming Language :: Python :: 3
Classifier: Programming Language :: Python :: 3.7
Classifier: Programming Language :: Python :: 3.8
Requires-Dist: matplotlib (>=3.2.1,<4.0.0)
Requires-Dist: rich (>=3.3.1,<4.0.0)
Project-URL: Documentation, https://algovisdocs.netlify.app
Project-URL: Repository, https://github.com/hotshot07/algovis
